[{"rank": 37, "track_name": "The Fate of Ophelia", "artist_names": "Taylor Swift", "streams": 141310, "previous_rank": 36.0, "peak_rank": 2, "streak": 165, "image_url": "https://i.scdn.co/image/ab67616d00001e0221fc8957d575e1ed7ab42594", "total_days": 165.0, "lastfm_tags": "pop; best of 2025; baroque pop; synthpop; love at first listen", "pop_flag": true, "album": "The Life of a Showgirl", "release_date": "", "days_since_release": ""}, {"rank": 194, "track_name": "Opalite", "artist_names": "Taylor Swift", "streams": 59210, "previous_rank": null, "peak_rank": 8, "streak": 1, "image_url": "https://i.scdn.co/image/ab67616d00001e02584b609b373960af2492e448", "total_days": null, "lastfm_tags": "pop; synthpop; soft rock; rnb; christmas", "pop_flag": true, "album": "The Life of a Showgirl", "release_date": "", "days_since_release": ""}]