{
  "album": "1989 (Taylor's Version)",
  "section": "standard_edition_tv",
  "track_count": 16,
  "tracks": [
    {
      "title": "Welcome To New York (Taylor's Version)",
      "url": "https://open.spotify.com/intl-fr/track/1hR8BSuEqPCCZfv93zzzz9",
      "type": "alternate_version",
      "edition": "standard",
      "display_section": "standard edition",
      "display_order": 1,
      "base_title": "Welcome To New York"
    },
    {
      "title": "Blank Space (Taylor's Version)",
      "url": "https://open.spotify.com/intl-fr/track/45wMBGri1PORPjM9PwFfrS",
      "type": "alternate_version",
      "edition": "standard",
      "display_section": "standard edition",
      "display_order": 2,
      "base_title": "Blank Space"
    },
    {
      "title": "Style (Taylor's Version)",
      "url": "https://open.spotify.com/intl-fr/track/1hjRhYpWyqDpPahmSlUTlc",
      "type": "alternate_version",
      "edition": "standard",
      "display_section": "standard edition",
      "display_order": 3,
      "base_title": "Style"
    },
    {
      "title": "Out Of The Woods (Taylor's Version)",
      "url": "https://open.spotify.com/intl-fr/track/045ZeOHPIzhxxsm8bq5kyE",
      "type": "alternate_version",
      "edition": "standard",
      "display_section": "standard edition",
      "display_order": 4,
      "base_title": "Out Of The Woods"
    },
    {
      "title": "All You Had To Do Was Stay (Taylor's Version)",
      "url": "https://open.spotify.com/intl-fr/track/6GXgd1BPD9bUpqw5AntGV5",
      "type": "alternate_version",
      "edition": "standard",
      "display_section": "standard edition",
      "display_order": 5,
      "base_title": "All You Had To Do Was Stay"
    },
    {
      "title": "Shake It Off (Taylor's Version)",
      "url": "https://open.spotify.com/intl-fr/track/3pv7Q5v2dpdefwdWIvE7yH",
      "type": "alternate_version",
      "edition": "standard",
      "display_section": "standard edition",
      "display_order": 6,
      "base_title": "Shake It Off"
    },
    {
      "title": "I Wish You Would (Taylor's Version)",
      "url": "https://open.spotify.com/intl-fr/track/43y1WpBdnEy5TR9aZoSQL9",
      "type": "alternate_version",
      "edition": "standard",
      "display_section": "standard edition",
      "display_order": 7,
      "base_title": "I Wish You Would"
    },
    {
      "title": "Bad Blood (Taylor's Version)",
      "url": "https://open.spotify.com/intl-fr/track/64FzgoLZ3oXu2SriZblHic",
      "type": "alternate_version",
      "edition": "standard",
      "display_section": "standard edition",
      "display_order": 8,
      "base_title": "Bad Blood"
    },
    {
      "title": "Wildest Dreams (Taylor's Version)",
      "url": "https://open.spotify.com/intl-fr/track/1K39ty6o1sHwwlZwO6a7wK",
      "type": "alternate_version",
      "edition": "standard",
      "display_section": "standard edition",
      "display_order": 9,
      "base_title": "Wildest Dreams"
    },
    {
      "title": "How You Get The Girl (Taylor's Version)",
      "url": "https://open.spotify.com/intl-fr/track/733OhaXQIHY7BKtY3vnSkn",
      "type": "alternate_version",
      "edition": "standard",
      "display_section": "standard edition",
      "display_order": 10,
      "base_title": "How You Get The Girl"
    },
    {
      "title": "This Love (Taylor's Version)",
      "url": "https://open.spotify.com/intl-fr/track/4WBEj8TeGtRPNJdOmT3WJW",
      "type": "alternate_version",
      "edition": "standard",
      "display_section": "standard edition",
      "display_order": 11,
      "base_title": "This Love"
    },
    {
      "title": "Clean (Taylor's Version)",
      "url": "https://open.spotify.com/intl-fr/track/0lKUBmEyQfzsQHozyeXzES",
      "type": "alternate_version",
      "edition": "standard",
      "display_section": "standard edition",
      "display_order": 12,
      "base_title": "Clean"
    },
    {
      "title": "New Romantics (Taylor's Version)",
      "url": "https://open.spotify.com/intl-fr/track/5M787RexsAiVYjQusM98CV",
      "type": "alternate_version",
      "edition": "standard",
      "display_section": "standard edition",
      "display_order": 13,
      "base_title": "New Romantics"
    },
    {
      "title": "Wonderland (Taylor's Version)",
      "url": "https://open.spotify.com/intl-fr/track/6HRsJu8vcnzYDN4t0570FY",
      "type": "alternate_version",
      "edition": "standard",
      "display_section": "standard edition",
      "display_order": 14,
      "base_title": "Wonderland"
    },
    {
      "title": "You Are In Love (Taylor's Version)",
      "url": "https://open.spotify.com/intl-fr/track/0TyGh27YQ5LknmiDhCzJiT",
      "type": "alternate_version",
      "edition": "standard",
      "display_section": "standard edition",
      "display_order": 15,
      "base_title": "You Are In Love"
    },
    {
      "title": "I Know Places (Taylor's Version)",
      "url": "https://open.spotify.com/track/1ULabO0PEsdJekqVH6G10G",
      "type": "alternate_version",
      "edition": "standard",
      "display_section": "standard edition",
      "display_order": 16,
      "base_title": "I Know Places"
    },
    {
      "title": "\"Slut!\" (Taylor's Version) (From The Vault)",
      "url": "https://open.spotify.com/intl-fr/track/0CD7DzeCsuPJygddqlUVYa",
      "type": "standalone",
      "edition": "standard",
      "display_section": "from the vault",
      "display_order": 1,
      "base_title": "\"Slut!\" (Taylor's Version) (From The Vault)"
    },
    {
      "title": "Is It Over Now? (Taylor's Version) (From The Vault)",
      "url": "https://open.spotify.com/intl-fr/track/6IG3sQ8s9nfk6TUlVzRhbN",
      "type": "standalone",
      "edition": "standard",
      "display_section": "from the vault",
      "display_order": 2,
      "base_title": "Is It Over Now? (Taylor's Version) (From The Vault)"
    },
    {
      "title": "Now That We Don't Talk (Taylor's Version) (From The Vault)",
      "url": "https://open.spotify.com/intl-fr/track/5QUIK7ZtziW8kGWo8RqopF",
      "type": "standalone",
      "edition": "standard",
      "display_section": "from the vault",
      "display_order": 3,
      "base_title": "Now That We Don't Talk (Taylor's Version) (From The Vault)"
    },
    {
      "title": "Say Don't Go (Taylor's Version) (From The Vault)",
      "url": "https://open.spotify.com/intl-fr/track/3CCRVu4F91Qp2mnGjmWBrf",
      "type": "standalone",
      "edition": "standard",
      "display_section": "from the vault",
      "display_order": 4,
      "base_title": "Say Don't Go (Taylor's Version) (From The Vault)"
    },
    {
      "title": "Suburban Legends (Taylor's Version) (From The Vault)",
      "url": "https://open.spotify.com/intl-fr/track/6M9ppdfFjR1AbpUl3Y8DcV",
      "type": "standalone",
      "edition": "standard",
      "display_section": "from the vault",
      "display_order": 5,
      "base_title": "Suburban Legends (Taylor's Version) (From The Vault)"
    },
    {
      "title": "Bad Blood (feat. Kendrick Lamar) (Taylor's Version)",
      "url": "https://open.spotify.com/intl-fr/track/6qAcApH8obo8eqatCKUHd9",
      "type": "feature",
      "edition": "standard",
      "display_section": "standard edition",
      "display_order": 6,
      "base_title": "Bad Blood (feat. Kendrick Lamar)"
    }
  ]
}
