{
  "album": "folklore",
  "section": "standard_edition",
  "track_count": 16,
  "tracks": [
    {
      "title": "the 1",
      "url": "https://open.spotify.com/intl-fr/track/0Jlcvv8IykzHaSmj49uNW8",
      "type": "track",
      "edition": "standard",
      "display_section": "Standard Edition",
      "display_order": 1,
      "base_title": "the 1",
      "album": "folklore",
      "primary_artist": "Taylor Swift",
      "featured_artists": [],
      "artists": [
        "Taylor Swift"
      ],
      "title_clean": "the 1",
      "song_family": "the_1",
      "version_tag": "standard"
    },
    {
      "title": "cardigan",
      "url": "https://open.spotify.com/intl-fr/track/4R2kfaDFhslZEMJqAFNpdd",
      "type": "track",
      "edition": "standard",
      "display_section": "Standard Edition",
      "display_order": 2,
      "base_title": "cardigan",
      "album": "folklore",
      "primary_artist": "Taylor Swift",
      "featured_artists": [],
      "artists": [
        "Taylor Swift"
      ],
      "title_clean": "cardigan",
      "song_family": "cardigan",
      "version_tag": "standard"
    },
    {
      "title": "the last great american dynasty",
      "url": "https://open.spotify.com/intl-fr/track/2Eeur20xVqfUoM3Q7EFPFt",
      "type": "track",
      "edition": "standard",
      "display_section": "Standard Edition",
      "display_order": 3,
      "base_title": "the last great american dynasty",
      "album": "folklore",
      "primary_artist": "Taylor Swift",
      "featured_artists": [],
      "artists": [
        "Taylor Swift"
      ],
      "title_clean": "the last great american dynasty",
      "song_family": "the_last_great_american_dynasty",
      "version_tag": "standard"
    },
    {
      "title": "exile (feat. Bon Iver)",
      "url": "https://open.spotify.com/intl-fr/track/4pvb0WLRcMtbPGmtejJJ6y",
      "type": "feature",
      "edition": "standard",
      "display_section": "Extras",
      "display_order": 4,
      "base_title": "exile (feat. Bon Iver)",
      "album": "folklore",
      "primary_artist": "Taylor Swift",
      "featured_artists": [
        "Bon Iver"
      ],
      "artists": [
        "Taylor Swift",
        "Bon Iver"
      ],
      "title_clean": "exile",
      "song_family": "exile",
      "version_tag": "featured__feature"
    },
    {
      "title": "my tears ricochet",
      "url": "https://open.spotify.com/intl-fr/track/1MgV7FIyNxIG7WzMRJV5HC",
      "type": "track",
      "edition": "standard",
      "display_section": "Standard Edition",
      "display_order": 5,
      "base_title": "my tears ricochet",
      "album": "folklore",
      "primary_artist": "Taylor Swift",
      "featured_artists": [],
      "artists": [
        "Taylor Swift"
      ],
      "title_clean": "my tears ricochet",
      "song_family": "my_tears_ricochet",
      "version_tag": "standard"
    },
    {
      "title": "mirrorball",
      "url": "https://open.spotify.com/intl-fr/track/0ZNU020wNYvgW84iljPkPP",
      "type": "track",
      "edition": "standard",
      "display_section": "Standard Edition",
      "display_order": 6,
      "base_title": "mirrorball",
      "album": "folklore",
      "primary_artist": "Taylor Swift",
      "featured_artists": [],
      "artists": [
        "Taylor Swift"
      ],
      "title_clean": "mirrorball",
      "song_family": "mirrorball",
      "version_tag": "standard"
    },
    {
      "title": "seven",
      "url": "https://open.spotify.com/intl-fr/track/6KJqZcs9XDgVck7Lg9QOTC",
      "type": "track",
      "edition": "standard",
      "display_section": "Standard Edition",
      "display_order": 7,
      "base_title": "seven",
      "album": "folklore",
      "primary_artist": "Taylor Swift",
      "featured_artists": [],
      "artists": [
        "Taylor Swift"
      ],
      "title_clean": "seven",
      "song_family": "seven",
      "version_tag": "standard"
    },
    {
      "title": "august",
      "url": "https://open.spotify.com/intl-fr/track/3hUxzQpSfdDqwM3ZTFQY0K",
      "type": "track",
      "edition": "standard",
      "display_section": "Standard Edition",
      "display_order": 8,
      "base_title": "august",
      "album": "folklore",
      "primary_artist": "Taylor Swift",
      "featured_artists": [],
      "artists": [
        "Taylor Swift"
      ],
      "title_clean": "august",
      "song_family": "august",
      "version_tag": "standard"
    },
    {
      "title": "this is me trying",
      "url": "https://open.spotify.com/intl-fr/track/7kt9e9LFSpN1zQtYEl19o1",
      "type": "track",
      "edition": "standard",
      "display_section": "Standard Edition",
      "display_order": 9,
      "base_title": "this is me trying",
      "album": "folklore",
      "primary_artist": "Taylor Swift",
      "featured_artists": [],
      "artists": [
        "Taylor Swift"
      ],
      "title_clean": "this is me trying",
      "song_family": "this_is_me_trying",
      "version_tag": "standard"
    },
    {
      "title": "illicit affairs",
      "url": "https://open.spotify.com/intl-fr/track/2NmsngXHeC1GQ9wWrzhOMf",
      "type": "track",
      "edition": "standard",
      "display_section": "Standard Edition",
      "display_order": 10,
      "base_title": "illicit affairs",
      "album": "folklore",
      "primary_artist": "Taylor Swift",
      "featured_artists": [],
      "artists": [
        "Taylor Swift"
      ],
      "title_clean": "illicit affairs",
      "song_family": "illicit_affairs",
      "version_tag": "standard"
    },
    {
      "title": "invisible string",
      "url": "https://open.spotify.com/intl-fr/track/6VsvKPJ4xjVNKpI8VVZ3SV",
      "type": "track",
      "edition": "standard",
      "display_section": "Standard Edition",
      "display_order": 11,
      "base_title": "invisible string",
      "album": "folklore",
      "primary_artist": "Taylor Swift",
      "featured_artists": [],
      "artists": [
        "Taylor Swift"
      ],
      "title_clean": "invisible string",
      "song_family": "invisible_string",
      "version_tag": "standard"
    },
    {
      "title": "mad woman",
      "url": "https://open.spotify.com/intl-fr/track/2QDyYdZyhlP2fp79KZX8Bi",
      "type": "track",
      "edition": "standard",
      "display_section": "Standard Edition",
      "display_order": 12,
      "base_title": "mad woman",
      "album": "folklore",
      "primary_artist": "Taylor Swift",
      "featured_artists": [],
      "artists": [
        "Taylor Swift"
      ],
      "title_clean": "mad woman",
      "song_family": "mad_woman",
      "version_tag": "standard"
    },
    {
      "title": "epiphany",
      "url": "https://open.spotify.com/intl-fr/track/08fa9LFcFBTcilB3iq2e2A",
      "type": "track",
      "edition": "standard",
      "display_section": "Standard Edition",
      "display_order": 13,
      "base_title": "epiphany",
      "album": "folklore",
      "primary_artist": "Taylor Swift",
      "featured_artists": [],
      "artists": [
        "Taylor Swift"
      ],
      "title_clean": "epiphany",
      "song_family": "epiphany",
      "version_tag": "standard"
    },
    {
      "title": "betty",
      "url": "https://open.spotify.com/intl-fr/track/5kI4eCXXzyuIUXjQra0Cxi",
      "type": "track",
      "edition": "standard",
      "display_section": "Standard Edition",
      "display_order": 14,
      "base_title": "betty",
      "album": "folklore",
      "primary_artist": "Taylor Swift",
      "featured_artists": [],
      "artists": [
        "Taylor Swift"
      ],
      "title_clean": "betty",
      "song_family": "betty",
      "version_tag": "standard"
    },
    {
      "title": "peace",
      "url": "https://open.spotify.com/intl-fr/track/7MbT4I8qGntX4fMdqMQgke",
      "type": "track",
      "edition": "standard",
      "display_section": "Standard Edition",
      "display_order": 15,
      "base_title": "peace",
      "album": "folklore",
      "primary_artist": "Taylor Swift",
      "featured_artists": [],
      "artists": [
        "Taylor Swift"
      ],
      "title_clean": "peace",
      "song_family": "peace",
      "version_tag": "standard"
    },
    {
      "title": "hoax",
      "url": "https://open.spotify.com/intl-fr/track/6MWoRt97mnSTXZhu3ggi9C",
      "type": "track",
      "edition": "standard",
      "display_section": "Standard Edition",
      "display_order": 16,
      "base_title": "hoax",
      "album": "folklore",
      "primary_artist": "Taylor Swift",
      "featured_artists": [],
      "artists": [
        "Taylor Swift"
      ],
      "title_clean": "hoax",
      "song_family": "hoax",
      "version_tag": "standard"
    }
  ]
}